[
  { "displayName": "Rock" },
  { "displayName": "Metal" },
  { "displayName": "Pop" },
  { "displayName": "Electronic" },
  { "displayName": "Hip Hop" },
  { "displayName": "Jazz" },
  { "displayName": "Folk, World, & Country" },
  { "displayName": "Funk / Soul" },
  { "displayName": "Non-Music" },
  { "displayName": "Blues" },
  { "displayName": "K-pop" },
  { "displayName": "R&B" },
  { "displayName": "Reggae" },
  { "displayName": "Latin" },
  { "displayName": "Classical" },
  { "displayName": "Children's Music" }
]
